Metadata-Version: 2.1
Name: EvoOpt
Version: 0.14
Summary: EvoOpt: Python Implementation of State-of-Art Evolutionary Algorithms
Home-page: UNKNOWN
Author: Sin Yong Teng
Author-email: tsyet12@gmail.com
License: BSD 2-Clause
Keywords: Evolutionary,Optimization,Algorithm
Platform: UNKNOWN
Classifier: Development Status :: 3 - Alpha
Classifier: Intended Audience :: Developers
Classifier: Topic :: Software Development :: Build Tools
Classifier: License :: OSI Approved :: BSD License
Classifier: Programming Language :: Python :: 3
Classifier: Programming Language :: Python :: 3.4
Classifier: Programming Language :: Python :: 3.5
Classifier: Programming Language :: Python :: 3.6
